functoolsplus/__init__.py
functoolsplus/abc.py
functoolsplus/functors.py
functoolsplus/hof.py
functoolsplus/lazy.py
functoolsplus/monads.py
functoolsplus/collections/__init__.py
functoolsplus/collections/base.py
functoolsplus/collections/lists.py
functoolsplus/collections/streams.py
functoolsplus/containers/__init__.py
functoolsplus/containers/lazy.py
functoolsplus/containers/pipes.py
functoolsplus/utils/__init__.py
functoolsplus/utils/implementations.py
functoolsplus/utils/singletons.py
functoolsplus-0.0.1.dist-info/LICENSE
functoolsplus-0.0.1.dist-info/METADATA
functoolsplus-0.0.1.dist-info/WHEEL
functoolsplus-0.0.1.dist-info/top_level.txt
functoolsplus-0.0.1.dist-info/RECORD
